cacheio/__init__.py
cacheio/_adapter.py
cacheio/_async_adapter.py
cacheio/_cache_factory.py
cacheio/_config.py
cacheio/_types.py
cacheio/_utils.py
cacheio/decorators/__init__.py
cacheio/decorators/_async.py
cacheio/decorators/_sync.py
cacheio/mixins/__init__.py
cacheio/mixins/_async.py
cacheio/mixins/_sync.py
cacheio/protocols/__init__.py
cacheio/protocols/_adapter_protocol.py
cacheio/protocols/_async_adapter_protocol.py
cacheio-0.1.2.dist-info/LICENSE
cacheio-0.1.2.dist-info/METADATA
cacheio-0.1.2.dist-info/WHEEL
cacheio-0.1.2.dist-info/RECORD
