Metadata-Version: 2.1
Name: cacheio
Version: 0.1.2
Summary: cacheio is a flexible, user-friendly Python caching interface that unifies synchronous and asynchronous caching backends. It provides a consistent API for interacting with proven libraries—cachelib for synchronous caching and aiocache for asynchronous caching—allowing seamless integration of both styles in your applications. With configurable defaults, optional backend installation, and easy-to-use decorators, cacheio simplifies caching logic while minimizing dependencies.
Home-page: https://github.com/bnlucas/cacheio
License: MIT
Keywords: cache,caching,asyncio,synchronous,aiohttp,cachelib
Author: Nathan Lucas
Author-email: nlucas@bnlucas.com
Requires-Python: >=3.10,<4.0
Classifier: Development Status :: 3 - Alpha
Classifier: Intended Audience :: Developers
Classifier: License :: OSI Approved :: MIT License
Classifier: Operating System :: OS Independent
Classifier: Programming Language :: Python
Classifier: Programming Language :: Python :: 3
Classifier: Programming Language :: Python :: 3.10
Classifier: Programming Language :: Python :: 3.11
Classifier: Programming Language :: Python :: 3.12
Classifier: Topic :: Software Development :: Libraries :: Python Modules
Classifier: Topic :: System :: Systems Administration
Project-URL: Repository, https://github.com/bnlucas/cacheio
